splitbam/__init__.py
splitbam/splitbam.py
splitbam-0.1.6.dist-info/LICENSE
splitbam-0.1.6.dist-info/METADATA
splitbam-0.1.6.dist-info/WHEEL
splitbam-0.1.6.dist-info/entry_points.txt
splitbam-0.1.6.dist-info/top_level.txt
splitbam-0.1.6.dist-info/RECORD
