Metadata-Version: 2.1
Name: splitbam
Version: 0.1.6
Summary: Split a BAM file into two subsamples
Home-page: https://gitlab.com/aaylward/splitbam
Author: Anthony Aylward
Author-email: aaylward@salk.edu
License: UNKNOWN
Platform: UNKNOWN
Classifier: Programming Language :: Python :: 3
Classifier: License :: OSI Approved :: MIT License
Classifier: Operating System :: OS Independent
License-File: LICENSE
Requires-Dist: pysam
